{
  "id": "3927191",
  "name": "pet-home",
  "font_family": "iconfont",
  "css_prefix_text": "icon-",
  "description": "",
  "glyphs": [
    {
      "icon_id": "5131636",
      "name": "鸟",
      "font_class": "niao",
      "unicode": "e608",
      "unicode_decimal": 58888
    },
    {
      "icon_id": "6303448",
      "name": "鱼",
      "font_class": "yu",
      "unicode": "e68d",
      "unicode_decimal": 59021
    },
    {
      "icon_id": "6303455",
      "name": "狗",
      "font_class": "gou",
      "unicode": "e690",
      "unicode_decimal": 59024
    },
    {
      "icon_id": "6303466",
      "name": "老鼠",
      "font_class": "laoshu",
      "unicode": "e694",
      "unicode_decimal": 59028
    },
    {
      "icon_id": "6303471",
      "name": "猫",
      "font_class": "mao",
      "unicode": "e695",
      "unicode_decimal": 59029
    },
    {
      "icon_id": "6303478",
      "name": "兔子",
      "font_class": "tuzi",
      "unicode": "e698",
      "unicode_decimal": 59032
    }
  ]
}
